MANIFEST.in
setup.cfg
setup.py
./setup.py
./build/lib/src/__init__.py
./build/lib/src/client.py
./build/lib/src/userapp.py
./src/__init__.py
./src/client.py
./src/userapp.py
./src/log/client_log_config.py
gb_cat4er_chat_client.egg-info/PKG-INFO
gb_cat4er_chat_client.egg-info/SOURCES.txt
gb_cat4er_chat_client.egg-info/dependency_links.txt
gb_cat4er_chat_client.egg-info/top_level.txt
src/__init__.py
src/client.py
src/userapp.py