Metadata-Version: 1.0
Name: gb-cat4er-chat-client
Version: 0.1
Summary: Client package for chat
Home-page: https://github.com/cat4er
Author: Victor Pavlyuk
Author-email: mooncat4er@ya.ru
License: UNKNOWN
Platform: UNKNOWN
